Metadata-Version: 2.1
Name: big-fish
Version: 0.6.2
Summary: Toolbox for the analysis of smFISH images.
Home-page: https://github.com/fish-quant/big-fish
Author: Arthur Imbert
Author-email: arthur.imbert.pro@gmail.com
License: BSD 3-Clause License
Platform: UNKNOWN
Classifier: Development Status :: 5 - Production/Stable
Classifier: Intended Audience :: Science/Research
Classifier: Intended Audience :: Developers
Classifier: Topic :: Software Development
Classifier: Topic :: Scientific/Engineering
Classifier: Topic :: Scientific/Engineering :: Bio-Informatics
Classifier: Topic :: Scientific/Engineering :: Artificial Intelligence
Classifier: Topic :: Scientific/Engineering :: Image Processing
Classifier: Topic :: Scientific/Engineering :: Image Recognition
Classifier: Operating System :: Unix
Classifier: Operating System :: MacOS
Classifier: Programming Language :: Python
Classifier: Programming Language :: Python :: 3.6
Classifier: Programming Language :: Python :: 3.7
Classifier: Programming Language :: Python :: 3.8
Classifier: Programming Language :: Python :: 3.9
Classifier: License :: OSI Approved :: BSD License
Requires-Python: >=3.6
License-File: LICENSE
Requires-Dist: numpy (>=1.16.0)
Requires-Dist: scikit-learn (>=0.24.0)
Requires-Dist: scikit-image (>=0.14.2)
Requires-Dist: scipy (>=1.4.1)
Requires-Dist: matplotlib (>=3.0.2)
Requires-Dist: pandas (>=0.24.0)
Requires-Dist: mrc (>=0.1.5)
Provides-Extra: deeplearning
Requires-Dist: tensorflow (==2.3.0) ; extra == 'deeplearning'
Requires-Dist: tensorflow-addons (==0.12.1) ; extra == 'deeplearning'
